py_roma-1.0.0.dist-info/licenses/LICENSE
roma/__init__.py
roma/art/__init__.py
roma/art/commander.py
roma/art/easel.py
roma/art/frame.py
roma/art/shortcuts.py
roma/art/tipbox.py
roma/art/resources/goose64.ico
roma/art/tkutils/__init__.py
roma/art/tkutils/misc.py
roma/art/tkutils/simple_dialogs.py
roma/console/console/__init__.py
roma/console/console/console.py
roma/console/console/printer.py
roma/ideology/__init__.py
roma/ideology/noear.py
roma/mercurius/__init__.py
roma/mercurius/city.py
roma/mercurius/hall.py
roma/mercurius/io.py
roma/mercurius/library/__init__.py
roma/mercurius/library/basic.py
roma/mercurius/library/commu.py
roma/mercurius/library/scroll.py
roma/spqr/__init__.py
roma/spqr/arguments.py
roma/spqr/atticus.py
roma/spqr/censor.py
roma/spqr/finder.py
roma/spqr/table.py
roma/spqr/threading.py
roma/spqr/wizard.py
py_roma-1.0.0.dist-info/METADATA
py_roma-1.0.0.dist-info/WHEEL
py_roma-1.0.0.dist-info/top_level.txt
py_roma-1.0.0.dist-info/RECORD
