Metadata-Version: 2.4
Name: py-roma
Version: 1.0.0
Summary: A python development kit containing handy packages.
Home-page: https://github.com/WilliamRo/roma
Download-URL: https://github.com/WilliamRo/roma/tarball/v1.0.0
Author: William Ro
Author-email: William Ro <walienluo@gmail.com>
Project-URL: Homepage, https://github.com/WilliamRo/roma
Project-URL: Issues, https://github.com/WilliamRo/roma/issues
Classifier: Development Status :: 2 - Pre-Alpha
Classifier: Intended Audience :: Developers
Classifier: License :: OSI Approved :: Apache Software License
Classifier: Natural Language :: English
Classifier: Operating System :: OS Independent
Classifier: Programming Language :: Python :: 2
Classifier: Programming Language :: Python :: 3
Classifier: Topic :: Utilities
Requires-Python: >=3.9
License-File: LICENSE
Dynamic: author
Dynamic: download-url
Dynamic: home-page
Dynamic: license-file
